dwave/experimental/__init__.py
dwave/experimental/automorphism/__init__.py
dwave/experimental/automorphism/automorphism_composite.py
dwave/experimental/automorphism/automorphism_generation.py
dwave/experimental/fast_reverse_anneal/__init__.py
dwave/experimental/fast_reverse_anneal/api.py
dwave/experimental/fast_reverse_anneal/schedule.py
dwave/experimental/fast_reverse_anneal/data/schedules.json
dwave/experimental/multicolor_anneal/__init__.py
dwave/experimental/multicolor_anneal/api.py
dwave/experimental/multicolor_anneal/utils.py
dwave/experimental/shimming/__init__.py
dwave/experimental/shimming/flux_biases.py
dwave/experimental/shimming/testing.py
dwave_experimental-2026.1.23.dist-info/licenses/LICENSE
dwave_experimental-2026.1.23.dist-info/METADATA
dwave_experimental-2026.1.23.dist-info/WHEEL
dwave_experimental-2026.1.23.dist-info/top_level.txt
dwave_experimental-2026.1.23.dist-info/RECORD
