Metadata-Version: 2.4
Name: dwave-experimental
Version: 2026.1.23
Summary: Ocean utilities to support advanced QPU prototype features.
Author-email: "D-Wave Inc." <tools@dwavesys.com>
License-Expression: Apache-2.0
Project-URL: Issues, https://github.com/dwavesystems/dwave-experimental/issues
Project-URL: Repository, https://github.com/dwavesystems/dwave-experimental.git
Classifier: Development Status :: 3 - Alpha
Classifier: Intended Audience :: Developers
Classifier: Intended Audience :: Science/Research
Classifier: Operating System :: OS Independent
Classifier: Programming Language :: Python :: 3
Requires-Python: !=3.14.1,>=3.10
License-File: LICENSE
Requires-Dist: dimod<0.13,>=0.12.20
Requires-Dist: dwave-cloud-client<0.15,>=0.13.6
Requires-Dist: dwave-samplers<2,>=1
Requires-Dist: dwave-system<2,>=1.32.0
Requires-Dist: matplotlib<4,>=3
Requires-Dist: minorminer<0.3,>=0.2.21
Requires-Dist: numpy<3,>=2
Dynamic: license-file
